ares_mcp_server/__init__.py
ares_mcp_server/api_client.py
ares_mcp_server/server.py
ares_mcp_server/tools.py
ares_mcp_server-0.3.2.dist-info/METADATA
ares_mcp_server-0.3.2.dist-info/WHEEL
ares_mcp_server-0.3.2.dist-info/entry_points.txt
ares_mcp_server-0.3.2.dist-info/licenses/LICENSE
ares_mcp_server-0.3.2.dist-info/RECORD
