Metadata-Version: 2.4
Name: ares-mcp-server
Version: 0.3.2
Summary: MCP server for Czech ARES (Administrative Registry of Economic Subjects) API v3
Project-URL: Homepage, https://github.com/vzeman/ares-mcp-server
Project-URL: Bug Tracker, https://github.com/vzeman/ares-mcp-server/issues
Project-URL: Documentation, https://github.com/vzeman/ares-mcp-server#readme
Project-URL: Source Code, https://github.com/vzeman/ares-mcp-server
Author-email: ARES MCP Server <contact@example.com>
License: MIT
License-File: LICENSE
Keywords: api,ares,business,czech,economic-subjects,mcp,registry
Classifier: Development Status :: 4 - Beta
Classifier: Intended Audience :: Developers
Classifier: License :: OSI Approved :: MIT License
Classifier: Operating System :: OS Independent
Classifier: Programming Language :: Python :: 3
Classifier: Programming Language :: Python :: 3.8
Classifier: Programming Language :: Python :: 3.9
Classifier: Programming Language :: Python :: 3.10
Classifier: Programming Language :: Python :: 3.11
Classifier: Programming Language :: Python :: 3.12
Classifier: Topic :: Internet :: WWW/HTTP :: Dynamic Content
Classifier: Topic :: Software Development :: Libraries :: Python Modules
Requires-Python: >=3.8
Requires-Dist: httpx>=0.24.0
Requires-Dist: mcp>=1.0.0
Requires-Dist: pydantic>=2.0.0
Requires-Dist: python-dotenv>=1.0.0
Provides-Extra: dev
Requires-Dist: black>=23.0.0; extra == 'dev'
Requires-Dist: mypy>=1.0.0; extra == 'dev'
Requires-Dist: pytest-asyncio>=0.21.0; extra == 'dev'
Requires-Dist: pytest-cov>=4.0.0; extra == 'dev'
Requires-Dist: pytest>=7.0.0; extra == 'dev'
Requires-Dist: ruff>=0.0.280; extra == 'dev'
Requires-Dist: types-python-dotenv>=1.0.0; extra == 'dev'
